pyg3t/__init__.py
pyg3t/annotate.py
pyg3t/batch.py
pyg3t/charsets.py
pyg3t/gtcat.py
pyg3t/gtcheckargs.py
pyg3t/gtcompare.py
pyg3t/gtdifflib.py
pyg3t/gtgrep.py
pyg3t/gtmerge.py
pyg3t/gtparse.py
pyg3t/gtprevmsgdiff.py
pyg3t/gtwdiff.py
pyg3t/gtxml.py
pyg3t/message.py
pyg3t/poabc.py
pyg3t/podiff.py
pyg3t/popatch.py
pyg3t/poselect.py
pyg3t/util.py
pyg3t-0.6.0.dist-info/COPYING
pyg3t-0.6.0.dist-info/LICENSE
pyg3t-0.6.0.dist-info/METADATA
pyg3t-0.6.0.dist-info/WHEEL
pyg3t-0.6.0.dist-info/entry_points.txt
pyg3t-0.6.0.dist-info/top_level.txt
pyg3t-0.6.0.dist-info/RECORD
