Metadata-Version: 2.1
Name: pyg3t
Version: 0.6.0
Summary: PyG3T, python gettext translation toolkit
Project-URL: Repository, https://gitlab.com/pyg3t/pyg3t
Requires-Python: >=3.8
License-File: LICENSE
License-File: COPYING
